py4vtile/__init__.py
py4vtile/geom.py
py4vtile/hashit.py
py4vtile/settings.py
py4vtile/settings_private.py
py4vtile/pbfpp/__init__.py
py4vtile/pbfpp/common.py
py4vtile/pbfpp/models.py
py4vtile-0.0.2.dist-info/LICENSE
py4vtile-0.0.2.dist-info/METADATA
py4vtile-0.0.2.dist-info/WHEEL
py4vtile-0.0.2.dist-info/top_level.txt
py4vtile-0.0.2.dist-info/RECORD
